{
  "users": [
    {
      "id": 1,
      "name": "George",
      "username": "george1",
      "password": "12345",
      "email": "george@email.com",
      "address": "555 Sun Road"
    },
    {
      "id": 2,
      "name": "Paul",
      "username": "paul2",
      "password": "12345",
      "email": "paul@email.com",
      "address": "12 Penny Lane"
    }
  ],
  "accounts": [
    {
      "id": 1,
      "type": "Checking",
      "balance": 2000,
      "userId": 1
    },
    {
      "id": 2,
      "type": "Savings",
      "balance": 6100,
      "userId": 1
    },
    {
      "id": 3,
      "type": "Checking",
      "balance": 100,
      "userId": 2
    },
    {
      "id": 4,
      "type": "Savings",
      "balance": 870,
      "userId": 2
    }
  ],
  "transactions": [
    {
      "id": 1,
      "type": "deposit",
      "amount": 50,
      "userId": 1,
      "accountId": 1
    },
    {
      "type": "deposit",
      "amount": 50,
      "userId": 1,
      "accountId": 1,
      "id": 2
    },
    {
      "type": "Deposit",
      "amount": "20",
      "userId": "1",
      "accountId": "1",
      "id": 3
    },
    {
      "type": "Deposit",
      "amount": "100.50",
      "userId": "1",
      "accountId": "1",
      "id": 4
    },
    {
      "type": "Deposit",
      "amount": "50",
      "userId": "1",
      "accountId": "1",
      "id": 5
    },
    {
      "type": "Deposit",
      "amount": "50",
      "userId": "1",
      "accountId": "1",
      "id": 6
    },
    {
      "type": "Deposit",
      "amount": "50",
      "userId": "1",
      "accountId": "1",
      "id": 7
    },
    {
      "type": "Deposit",
      "amount": "50",
      "userId": "1",
      "accountId": "1",
      "id": 8
    },
    {
      "type": "Deposit",
      "amount": "50",
      "userId": "1",
      "accountId": "1",
      "id": 9
    },
    {
      "type": "Deposit",
      "amount": "5",
      "userId": "1",
      "accountId": "1",
      "id": 10
    },
    {
      "type": "Deposit",
      "amount": "5",
      "userId": "1",
      "accountId": "1",
      "id": 11
    },
    {
      "type": "Deposit",
      "amount": "5",
      "userId": "1",
      "accountId": "1",
      "id": 12
    },
    {
      "type": "Deposit",
      "amount": "100",
      "userId": "1",
      "accountId": "1",
      "id": 13
    },
    {
      "type": "Deposit",
      "amount": "300",
      "userId": "1",
      "accountId": "1",
      "id": 14
    },
    {
      "type": "Deposit",
      "amount": "2",
      "userId": "1",
      "accountId": "1",
      "id": 15
    },
    {
      "type": "Deposit",
      "amount": "1000",
      "userId": "1",
      "accountId": "2",
      "id": 16
    },
    {
      "type": "Deposit",
      "amount": "100",
      "userId": "1",
      "accountId": "2",
      "id": 17
    },
    {
      "type": "Withdrawl",
      "amount": "2",
      "userId": "1",
      "accountId": "1",
      "id": 18
    },
    {
      "type": "Transfer",
      "amount": "20",
      "userId": "1",
      "accountId": "1",
      "id": 19
    },
    {
      "type": "Transfer",
      "amount": "20",
      "userId": "1",
      "accountId": "2",
      "id": 20
    },
    {
      "type": "Transfer",
      "amount": "1000",
      "userId": "1",
      "accountId": "2",
      "id": 21
    },
    {
      "type": "Transfer",
      "amount": "1000",
      "userId": "1",
      "accountId": "1",
      "id": 22
    },
    {
      "type": "Withdrawl",
      "amount": "1000",
      "userId": "1",
      "accountId": "1",
      "id": 23
    },
    {
      "type": "Deposit",
      "amount": "300",
      "userId": "1",
      "accountId": "2",
      "id": 24
    },
    {
      "type": "Withdrawl",
      "amount": "500",
      "userId": "1",
      "accountId": "1",
      "id": 25
    },
    {
      "type": "Deposit",
      "amount": "1000",
      "userId": "1",
      "accountId": "2",
      "id": 26
    },
    {
      "type": "Withdrawl",
      "amount": "480",
      "userId": "1",
      "accountId": "1",
      "id": 27
    },
    {
      "type": "Deposit",
      "amount": "80",
      "userId": "1",
      "accountId": "2",
      "id": 28
    },
    {
      "type": "Withdrawl",
      "amount": "100",
      "userId": "1",
      "accountId": "2",
      "id": 29
    },
    {
      "type": "Deposit",
      "amount": "100",
      "userId": "1",
      "accountId": "1",
      "id": 30
    },
    {
      "type": "Withdrawl",
      "amount": "100",
      "userId": "1",
      "accountId": "1",
      "id": 31
    },
    {
      "type": "Withdrawl",
      "amount": "400",
      "userId": "1",
      "accountId": "2",
      "id": 32
    },
    {
      "type": "Deposit",
      "amount": "100",
      "userId": "1",
      "accountId": "2",
      "id": 33
    },
    {
      "type": "Deposit",
      "amount": "1000",
      "userId": "2",
      "accountId": "4",
      "id": 34
    },
    {
      "type": "Withdrawl",
      "amount": "30",
      "userId": "2",
      "accountId": "4",
      "id": 35
    },
    {
      "type": "Transfer",
      "amount": "100",
      "userId": "2",
      "accountId": "4",
      "id": 36
    },
    {
      "type": "Transfer",
      "amount": "100",
      "userId": "2",
      "accountId": "3",
      "id": 37
    }
  ]
}